cvlayer/__init__.py
cvlayer/cvwindow.py
cvlayer/chrono/__init__.py
cvlayer/chrono/datetime_filename.py
cvlayer/cv/__init__.py
cvlayer/cv/angle.py
cvlayer/cv/aspect_ratio.py
cvlayer/cv/backend.py
cvlayer/cv/basic.py
cvlayer/cv/bgsub.py
cvlayer/cv/bitwise.py
cvlayer/cv/border.py
cvlayer/cv/clip.py
cvlayer/cv/color.py
cvlayer/cv/colormap.py
cvlayer/cv/convert_scale_abs.py
cvlayer/cv/cvt_color.py
cvlayer/cv/dehaze.py
cvlayer/cv/fourcc.py
cvlayer/cv/fourier_transform.py
cvlayer/cv/histogram.py
cvlayer/cv/hough_lines.py
cvlayer/cv/hsv.py
cvlayer/cv/image_crop.py
cvlayer/cv/image_features.py
cvlayer/cv/image_flip.py
cvlayer/cv/image_io.py
cvlayer/cv/image_make.py
cvlayer/cv/image_move.py
cvlayer/cv/image_normalize.py
cvlayer/cv/image_resize.py
cvlayer/cv/image_rotation.py
cvlayer/cv/in_range.py
cvlayer/cv/intersection.py
cvlayer/cv/iou.py
cvlayer/cv/keymap.py
cvlayer/cv/kmeans.py
cvlayer/cv/match_template.py
cvlayer/cv/matcher.py
cvlayer/cv/mean_shift.py
cvlayer/cv/morphology.py
cvlayer/cv/mouse.py
cvlayer/cv/norm.py
cvlayer/cv/orb.py
cvlayer/cv/palette.py
cvlayer/cv/perspective.py
cvlayer/cv/pyramid.py
cvlayer/cv/roi.py
cvlayer/cv/rotate_tracer.py
cvlayer/cv/stabilizer.py
cvlayer/cv/stack.py
cvlayer/cv/term_criteria.py
cvlayer/cv/threshold.py
cvlayer/cv/tracker.py
cvlayer/cv/tracking.py
cvlayer/cv/video_capture.py
cvlayer/cv/video_writer.py
cvlayer/cv/window.py
cvlayer/cv/contour/__init__.py
cvlayer/cv/contour/analysis.py
cvlayer/cv/contour/component.py
cvlayer/cv/contour/contour.py
cvlayer/cv/contour/find.py
cvlayer/cv/contour/find_largest.py
cvlayer/cv/contour/moments.py
cvlayer/cv/contour/most_point.py
cvlayer/cv/contour/quadrant.py
cvlayer/cv/contour/deprecated/__init__.py
cvlayer/cv/contour/deprecated/edge.py
cvlayer/cv/drawable/__init__.py
cvlayer/cv/drawable/arrowed.py
cvlayer/cv/drawable/circle.py
cvlayer/cv/drawable/contours.py
cvlayer/cv/drawable/crosshair.py
cvlayer/cv/drawable/defaults.py
cvlayer/cv/drawable/ellipse.py
cvlayer/cv/drawable/image.py
cvlayer-0.32.0.dist-info/LICENSE
cvlayer-0.32.0.dist-info/METADATA
cvlayer-0.32.0.dist-info/WHEEL
cvlayer-0.32.0.dist-info/top_level.txt
cvlayer-0.32.0.dist-info/RECORD
