Metadata-Version: 2.1
Name: cvlayer
Version: 0.32.0
Summary: OpenCV Layer Helper
Home-page: https://github.com/osom8979/cvlayer
Author: zer0
Author-email: osom8979@gmail.com
Maintainer: zer0
Maintainer-email: osom8979@gmail.com
License: MIT License
Project-URL: GitHub: issues, https://github.com/osom8979/cvlayer/issues
Project-URL: GitHub: repo, https://github.com/osom8979/cvlayer
Platform: UNKNOWN
Classifier: Development Status :: 4 - Beta
Classifier: Intended Audience :: Developers
Classifier: Intended Audience :: Science/Research
Classifier: License :: OSI Approved :: MIT License
Classifier: Operating System :: OS Independent
Classifier: Programming Language :: Python
Classifier: Programming Language :: Python :: 3.10
Classifier: Programming Language :: Python :: 3.11
Classifier: Programming Language :: Python :: 3.9
Classifier: Topic :: Scientific/Engineering :: Image Processing
Requires-Python: >=3.9
License-File: LICENSE
Requires-Dist: numpy
Provides-Extra: headless
Requires-Dist: opencv-python-headless ; extra == 'headless'
Provides-Extra: opencv
Requires-Dist: opencv-python ; extra == 'opencv'
